[{"puzzle": "..9......83.5........4791..5....843.....9.....142....6..1284........5.81......6..", "id": 0, "best": "00:06:06 ", "time": "00:21:20"}, {"puzzle": "1..485..9.3.7.6.............789.....6..8.4..9.....362.............1.5.8.8..976..5", "id": 1, "best": "00:07:14 ", "time": "00:17:04"}, {"puzzle": "8....3.7....6...9.......2...5.........7.451.....7...3...1..8.9....5......68.1.4..", "id": 2, "best": "00:10:23 ", "time": "00:40:45"}, {"puzzle": "8....3.7....6...9.......2...5.........7.451.....7...3...1..8.9....5......68.1.4..", "id": 3, "best": "00:10:23 ", "time": "00:40:45"}, {"puzzle": "8....3.7....6...9.......2...5.........7.451.....7...3...1..8.9....5......68.1.4..", "id": 4, "best": "00:10:23 ", "time": "00:40:45"}, {"puzzle": "8....3.7....6...9.......2...5.........7.451.....7...3...1..8.9....5......68.1.4..", "id": 5, "best": "00:10:23 ", "time": "00:40:45"}, {"puzzle": "8....3.7....6...9.......2...5.........7.451.....7...3...1..8.9....5......68.1.4..", "id": 6, "best": "00:10:23 ", "time": "00:40:45"}, {"puzzle": "8....3.7....6...9.......2...5.........7.451.....7...3...1..8.9....5......68.1.4..", "id": 7, "best": "00:10:23 ", "time": "00:40:45"}, {"puzzle": "8....3.7....6...9.......2...5.........7.451.....7...3...1..8.9....5......68.1.4..", "id": 8, "best": "00:10:23 ", "time": "00:40:45"}, {"puzzle": "8....3.7....6...9.......2...5.........7.451.....7...3...1..8.9....5......68.1.4..", "id": 9, "best": "00:10:23 ", "time": "00:40:45"}, {"puzzle": "8....3.7....6...9.......2...5.........7.451.....7...3...1..8.9....5......68.1.4..", "id": 10, "best": "00:10:23 ", "time": "00:40:45"}, {"puzzle": "8....3.7....6...9.......2...5.........7.451.....7...3...1..8.9....5......68.1.4..", "id": 11, "best": "00:10:23 ", "time": "00:40:45"}, {"puzzle": "8....3.7....6...9.......2...5.........7.451.....7...3...1..8.9....5......68.1.4..", "id": 12, "best": "00:10:23 ", "time": "00:40:45"}, {"puzzle": "8....3.7....6...9.......2...5.........7.451.....7...3...1..8.9....5......68.1.4..", "id": 13, "best": "00:10:23 ", "time": "00:40:45"}, {"puzzle": "8....3.7....6...9.......2...5.........7.451.....7...3...1..8.9....5......68.1.4..", "id": 14, "best": "00:10:23 ", "time": "00:40:45"}, {"puzzle": "8....3.7....6...9.......2...5.........7.451.....7...3...1..8.9....5......68.1.4..", "id": 15, "best": "00:10:23 ", "time": "00:40:45"}, {"puzzle": "8....3.7....6...9.......2...5.........7.451.....7...3...1..8.9....5......68.1.4..", "id": 16, "best": "00:10:23 ", "time": "00:40:45"}, {"puzzle": "8....3.7....6...9.......2...5.........7.451.....7...3...1..8.9....5......68.1.4..", "id": 17, "best": "00:10:23 ", "time": "00:40:45"}, {"puzzle": "8....3.7....6...9.......2...5.........7.451.....7...3...1..8.9....5......68.1.4..", "id": 18, "best": "00:10:23 ", "time": "00:40:45"}, {"puzzle": "8....3.7....6...9.......2...5.........7.451.....7...3...1..8.9....5......68.1.4..", "id": 19, "best": "00:10:23 ", "time": "00:40:45"}, {"puzzle": "8....3.7....6...9.......2...5.........7.451.....7...3...1..8.9....5......68.1.4..", "id": 20, "best": "00:10:23 ", "time": "00:40:45"}, {"puzzle": "8....3.7....6...9.......2...5.........7.451.....7...3...1..8.9....5......68.1.4..", "id": 21, "best": "00:10:23 ", "time": "00:40:45"}, {"puzzle": "8....3.7....6...9.......2...5.........7.451.....7...3...1..8.9....5......68.1.4..", "id": 22, "best": "00:10:23 ", "time": "00:40:45"}, {"puzzle": "8....3.7....6...9.......2...5.........7.451.....7...3...1..8.9....5......68.1.4..", "id": 23, "best": "00:10:23 ", "time": "00:40:45"}, {"puzzle": "8....3.7....6...9.......2...5.........7.451.....7...3...1..8.9....5......68.1.4..", "id": 24, "best": "00:10:23 ", "time": "00:40:45"}, {"puzzle": "8....3.7....6...9.......2...5.........7.451.....7...3...1..8.9....5......68.1.4..", "id": 25, "best": "00:10:23 ", "time": "00:40:45"}, {"puzzle": "8....3.7....6...9.......2...5.........7.451.....7...3...1..8.9....5......68.1.4..", "id": 26, "best": "00:10:23 ", "time": "00:40:45"}, {"puzzle": "8....3.7....6...9.......2...5.........7.451.....7...3...1..8.9....5......68.1.4..", "id": 27, "best": "00:10:23 ", "time": "00:40:45"}, {"puzzle": "8....3.7....6...9.......2...5.........7.451.....7...3...1..8.9....5......68.1.4..", "id": 28, "best": "00:10:23 ", "time": "00:40:45"}, {"puzzle": "8....3.7....6...9.......2...5.........7.451.....7...3...1..8.9....5......68.1.4..", "id": 29, "best": "00:10:23 ", "time": "00:40:45"}, {"puzzle": "8....3.7....6...9.......2...5.........7.451.....7...3...1..8.9....5......68.1.4..", "id": 30, "best": "00:10:23 ", "time": "00:40:45"}, {"puzzle": "8....3.7....6...9.......2...5.........7.451.....7...3...1..8.9....5......68.1.4..", "id": 31, "best": "00:10:23 ", "time": "00:40:45"}, {"puzzle": "8....3.7....6...9.......2...5.........7.451.....7...3...1..8.9....5......68.1.4..", "id": 32, "best": "00:10:23 ", "time": "00:40:45"}, {"puzzle": "8....3.7....6...9.......2...5.........7.451.....7...3...1..8.9....5......68.1.4..", "id": 33, "best": "00:10:23 ", "time": "00:40:45"}, {"puzzle": "8....3.7....6...9.......2...5.........7.451.....7...3...1..8.9....5......68.1.4..", "id": 34, "best": "00:10:23 ", "time": "00:40:45"}, {"puzzle": "8....3.7....6...9.......2...5.........7.451.....7...3...1..8.9....5......68.1.4..", "id": 35, "best": "00:10:23 ", "time": "00:40:45"}, {"puzzle": "8....3.7....6...9.......2...5.........7.451.....7...3...1..8.9....5......68.1.4..", "id": 36, "best": "00:10:23 ", "time": "00:40:45"}, {"puzzle": "8....3.7....6...9.......2...5.........7.451.....7...3...1..8.9....5......68.1.4..", "id": 37, "best": "00:10:23 ", "time": "00:40:45"}, {"puzzle": "8....3.7....6...9.......2...5.........7.451.....7...3...1..8.9....5......68.1.4..", "id": 38, "best": "00:10:23 ", "time": "00:40:45"}, {"puzzle": "8....3.7....6...9.......2...5.........7.451.....7...3...1..8.9....5......68.1.4..", "id": 39, "best": "00:10:23 ", "time": "00:40:45"}, {"puzzle": "8....3.7....6...9.......2...5.........7.451.....7...3...1..8.9....5......68.1.4..", "id": 40, "best": "00:10:23 ", "time": "00:40:45"}, {"puzzle": "8....3.7....6...9.......2...5.........7.451.....7...3...1..8.9....5......68.1.4..", "id": 41, "best": "00:10:23 ", "time": "00:40:45"}, {"puzzle": "8....3.7....6...9.......2...5.........7.451.....7...3...1..8.9....5......68.1.4..", "id": 42, "best": "00:10:23 ", "time": "00:40:45"}, {"puzzle": "8....3.7....6...9.......2...5.........7.451.....7...3...1..8.9....5......68.1.4..", "id": 43, "best": "00:10:23 ", "time": "00:40:45"}, {"puzzle": "8....3.7....6...9.......2...5.........7.451.....7...3...1..8.9....5......68.1.4..", "id": 44, "best": "00:10:23 ", "time": "00:40:45"}, {"puzzle": "8....3.7....6...9.......2...5.........7.451.....7...3...1..8.9....5......68.1.4..", "id": 45, "best": "00:10:23 ", "time": "00:40:45"}, {"puzzle": "8....3.7....6...9.......2...5.........7.451.....7...3...1..8.9....5......68.1.4..", "id": 46, "best": "00:10:23 ", "time": "00:40:45"}, {"puzzle": "8....3.7....6...9.......2...5.........7.451.....7...3...1..8.9....5......68.1.4..", "id": 47, "best": "00:10:23 ", "time": "00:40:45"}, {"puzzle": "8....3.7....6...9.......2...5.........7.451.....7...3...1..8.9....5......68.1.4..", "id": 48, "best": "00:10:23 ", "time": "00:40:45"}, {"puzzle": "8....3.7....6...9.......2...5.........7.451.....7...3...1..8.9....5......68.1.4..", "id": 49, "best": "00:10:23 ", "time": "00:40:45"}, {"puzzle": "8....3.7....6...9.......2...5.........7.451.....7...3...1..8.9....5......68.1.4..", "id": 50, "best": "00:10:23 ", "time": "00:40:45"}, {"puzzle": "8....3.7....6...9.......2...5.........7.451.....7...3...1..8.9....5......68.1.4..", "id": 51, "best": "00:10:23 ", "time": "00:40:45"}, {"puzzle": "8....3.7....6...9.......2...5.........7.451.....7...3...1..8.9....5......68.1.4..", "id": 52, "best": "00:10:23 ", "time": "00:40:45"}, {"puzzle": "8....3.7....6...9.......2...5.........7.451.....7...3...1..8.9....5......68.1.4..", "id": 53, "best": "00:10:23 ", "time": "00:40:45"}, {"puzzle": "8....3.7....6...9.......2...5.........7.451.....7...3...1..8.9....5......68.1.4..", "id": 54, "best": "00:10:23 ", "time": "00:40:45"}, {"puzzle": "8....3.7....6...9.......2...5.........7.451.....7...3...1..8.9....5......68.1.4..", "id": 55, "best": "00:10:23 ", "time": "00:40:45"}, {"puzzle": "8....3.7....6...9.......2...5.........7.451.....7...3...1..8.9....5......68.1.4..", "id": 56, "best": "00:10:23 ", "time": "00:40:45"}, {"puzzle": "8....3.7....6...9.......2...5.........7.451.....7...3...1..8.9....5......68.1.4..", "id": 57, "best": "00:10:23 ", "time": "00:40:45"}, {"puzzle": "8....3.7....6...9.......2...5.........7.451.....7...3...1..8.9....5......68.1.4..", "id": 58, "best": "00:10:23 ", "time": "00:40:45"}, {"puzzle": "8....3.7....6...9.......2...5.........7.451.....7...3...1..8.9....5......68.1.4..", "id": 59, "best": "00:10:23 ", "time": "00:40:45"}, {"puzzle": "8....3.7....6...9.......2...5.........7.451.....7...3...1..8.9....5......68.1.4..", "id": 60, "best": "00:10:23 ", "time": "00:40:45"}, {"puzzle": "8....3.7....6...9.......2...5.........7.451.....7...3...1..8.9....5......68.1.4..", "id": 61, "best": "00:10:23 ", "time": "00:40:45"}, {"puzzle": "8....3.7....6...9.......2...5.........7.451.....7...3...1..8.9....5......68.1.4..", "id": 62, "best": "00:10:23 ", "time": "00:40:45"}, {"puzzle": "8....3.7....6...9.......2...5.........7.451.....7...3...1..8.9....5......68.1.4..", "id": 63, "best": "00:10:23 ", "time": "00:40:45"}, {"puzzle": "8....3.7....6...9.......2...5.........7.451.....7...3...1..8.9....5......68.1.4..", "id": 64, "best": "00:10:23 ", "time": "00:40:45"}, {"puzzle": "8....3.7....6...9.......2...5.........7.451.....7...3...1..8.9....5......68.1.4..", "id": 65, "best": "00:10:23 ", "time": "00:40:45"}, {"puzzle": "8....3.7....6...9.......2...5.........7.451.....7...3...1..8.9....5......68.1.4..", "id": 66, "best": "00:10:23 ", "time": "00:40:45"}, {"puzzle": "8....3.7....6...9.......2...5.........7.451.....7...3...1..8.9....5......68.1.4..", "id": 67, "best": "00:10:23 ", "time": "00:40:45"}, {"puzzle": "8....3.7....6...9.......2...5.........7.451.....7...3...1..8.9....5......68.1.4..", "id": 68, "best": "00:10:23 ", "time": "00:40:45"}, {"puzzle": "8....3.7....6...9.......2...5.........7.451.....7...3...1..8.9....5......68.1.4..", "id": 69, "best": "00:10:23 ", "time": "00:40:45"}, {"puzzle": "8....3.7....6...9.......2...5.........7.451.....7...3...1..8.9....5......68.1.4..", "id": 70, "best": "00:10:23 ", "time": "00:40:45"}, {"puzzle": "8....3.7....6...9.......2...5.........7.451.....7...3...1..8.9....5......68.1.4..", "id": 71, "best": "00:10:23 ", "time": "00:40:45"}, {"puzzle": "8....3.7....6...9.......2...5.........7.451.....7...3...1..8.9....5......68.1.4..", "id": 72, "best": "00:10:23 ", "time": "00:40:45"}, {"puzzle": "8....3.7....6...9.......2...5.........7.451.....7...3...1..8.9....5......68.1.4..", "id": 73, "best": "00:10:23 ", "time": "00:40:45"}, {"puzzle": "8....3.7....6...9.......2...5.........7.451.....7...3...1..8.9....5......68.1.4..", "id": 74, "best": "00:10:23 ", "time": "00:40:45"}, {"puzzle": "8....3.7....6...9.......2...5.........7.451.....7...3...1..8.9....5......68.1.4..", "id": 75, "best": "00:10:23 ", "time": "00:40:45"}, {"puzzle": "8....3.7....6...9.......2...5.........7.451.....7...3...1..8.9....5......68.1.4..", "id": 76, "best": "00:10:23 ", "time": "00:40:45"}, {"puzzle": "8....3.7....6...9.......2...5.........7.451.....7...3...1..8.9....5......68.1.4..", "id": 77, "best": "00:10:23 ", "time": "00:40:45"}, {"puzzle": "8....3.7....6...9.......2...5.........7.451.....7...3...1..8.9....5......68.1.4..", "id": 78, "best": "00:10:23 ", "time": "00:40:45"}, {"puzzle": "8....3.7....6...9.......2...5.........7.451.....7...3...1..8.9....5......68.1.4..", "id": 79, "best": "00:10:23 ", "time": "00:40:45"}, {"puzzle": "8....3.7....6...9.......2...5.........7.451.....7...3...1..8.9....5......68.1.4..", "id": 80, "best": "00:10:23 ", "time": "00:40:45"}, {"puzzle": "8....3.7....6...9.......2...5.........7.451.....7...3...1..8.9....5......68.1.4..", "id": 81, "best": "00:10:23 ", "time": "00:40:45"}, {"puzzle": "8....3.7....6...9.......2...5.........7.451.....7...3...1..8.9....5......68.1.4..", "id": 82, "best": "00:10:23 ", "time": "00:40:45"}, {"puzzle": "8....3.7....6...9.......2...5.........7.451.....7...3...1..8.9....5......68.1.4..", "id": 83, "best": "00:10:23 ", "time": "00:40:45"}, {"puzzle": "8....3.7....6...9.......2...5.........7.451.....7...3...1..8.9....5......68.1.4..", "id": 84, "best": "00:10:23 ", "time": "00:40:45"}, {"puzzle": "8....3.7....6...9.......2...5.........7.451.....7...3...1..8.9....5......68.1.4..", "id": 85, "best": "00:10:23 ", "time": "00:40:45"}, {"puzzle": "8....3.7....6...9.......2...5.........7.451.....7...3...1..8.9....5......68.1.4..", "id": 86, "best": "00:10:23 ", "time": "00:40:45"}, {"puzzle": "8....3.7....6...9.......2...5.........7.451.....7...3...1..8.9....5......68.1.4..", "id": 87, "best": "00:10:23 ", "time": "00:40:45"}, {"puzzle": "8....3.7....6...9.......2...5.........7.451.....7...3...1..8.9....5......68.1.4..", "id": 88, "best": "00:10:23 ", "time": "00:40:45"}, {"puzzle": "8....3.7....6...9.......2...5.........7.451.....7...3...1..8.9....5......68.1.4..", "id": 89, "best": "00:10:23 ", "time": "00:40:45"}, {"puzzle": "8....3.7....6...9.......2...5.........7.451.....7...3...1..8.9....5......68.1.4..", "id": 90, "best": "00:10:23 ", "time": "00:40:45"}, {"puzzle": "8....3.7....6...9.......2...5.........7.451.....7...3...1..8.9....5......68.1.4..", "id": 91, "best": "00:10:23 ", "time": "00:40:45"}, {"puzzle": "8....3.7....6...9.......2...5.........7.451.....7...3...1..8.9....5......68.1.4..", "id": 92, "best": "00:10:23 ", "time": "00:40:45"}, {"puzzle": "8....3.7....6...9.......2...5.........7.451.....7...3...1..8.9....5......68.1.4..", "id": 93, "best": "00:10:23 ", "time": "00:40:45"}, {"puzzle": "8....3.7....6...9.......2...5.........7.451.....7...3...1..8.9....5......68.1.4..", "id": 94, "best": "00:10:23 ", "time": "00:40:45"}, {"puzzle": "8....3.7....6...9.......2...5.........7.451.....7...3...1..8.9....5......68.1.4..", "id": 95, "best": "00:10:23 ", "time": "00:40:45"}, {"puzzle": "8....3.7....6...9.......2...5.........7.451.....7...3...1..8.9....5......68.1.4..", "id": 96, "best": "00:10:23 ", "time": "00:40:45"}, {"puzzle": "8....3.7....6...9.......2...5.........7.451.....7...3...1..8.9....5......68.1.4..", "id": 97, "best": "00:10:23 ", "time": "00:40:45"}, {"puzzle": "8....3.7....6...9.......2...5.........7.451.....7...3...1..8.9....5......68.1.4..", "id": 98, "best": "00:10:23 ", "time": "00:40:45"}, {"puzzle": "8....3.7....6...9.......2...5.........7.451.....7...3...1..8.9....5......68.1.4..", "id": 99, "best": "00:10:23 ", "time": "00:40:45"}, {"puzzle": "8....3.7....6...9.......2...5.........7.451.....7...3...1..8.9....5......68.1.4..", "id": 100, "best": "00:10:23 ", "time": "00:40:45"}, {"puzzle": "8....3.7....6...9.......2...5.........7.451.....7...3...1..8.9....5......68.1.4..", "id": 101, "best": "00:10:23 ", "time": "00:40:45"}, {"puzzle": "8....3.7....6...9.......2...5.........7.451.....7...3...1..8.9....5......68.1.4..", "id": 102, "best": "00:10:23 ", "time": "00:40:45"}, {"puzzle": "8....3.7....6...9.......2...5.........7.451.....7...3...1..8.9....5......68.1.4..", "id": 103, "best": "00:10:23 ", "time": "00:40:45"}, {"puzzle": "8....3.7....6...9.......2...5.........7.451.....7...3...1..8.9....5......68.1.4..", "id": 104, "best": "00:10:23 ", "time": "00:40:45"}, {"puzzle": "8....3.7....6...9.......2...5.........7.451.....7...3...1..8.9....5......68.1.4..", "id": 105, "best": "00:10:23 ", "time": "00:40:45"}, {"puzzle": "8....3.7....6...9.......2...5.........7.451.....7...3...1..8.9....5......68.1.4..", "id": 106, "best": "00:10:23 ", "time": "00:40:45"}, {"puzzle": "8....3.7....6...9.......2...5.........7.451.....7...3...1..8.9....5......68.1.4..", "id": 107, "best": "00:10:23 ", "time": "00:40:45"}, {"puzzle": "8....3.7....6...9.......2...5.........7.451.....7...3...1..8.9....5......68.1.4..", "id": 108, "best": "00:10:23 ", "time": "00:40:45"}, {"puzzle": "8....3.7....6...9.......2...5.........7.451.....7...3...1..8.9....5......68.1.4..", "id": 109, "best": "00:10:23 ", "time": "00:40:45"}, {"puzzle": "8....3.7....6...9.......2...5.........7.451.....7...3...1..8.9....5......68.1.4..", "id": 110, "best": "00:10:23 ", "time": "00:40:45"}, {"puzzle": "8....3.7....6...9.......2...5.........7.451.....7...3...1..8.9....5......68.1.4..", "id": 111, "best": "00:10:23 ", "time": "00:40:45"}, {"puzzle": "8....3.7....6...9.......2...5.........7.451.....7...3...1..8.9....5......68.1.4..", "id": 112, "best": "00:10:23 ", "time": "00:40:45"}, {"puzzle": "8....3.7....6...9.......2...5.........7.451.....7...3...1..8.9....5......68.1.4..", "id": 113, "best": "00:10:23 ", "time": "00:40:45"}, {"puzzle": "8....3.7....6...9.......2...5.........7.451.....7...3...1..8.9....5......68.1.4..", "id": 114, "best": "00:10:23 ", "time": "00:40:45"}, {"puzzle": "8....3.7....6...9.......2...5.........7.451.....7...3...1..8.9....5......68.1.4..", "id": 115, "best": "00:10:23 ", "time": "00:40:45"}, {"puzzle": "8....3.7....6...9.......2...5.........7.451.....7...3...1..8.9....5......68.1.4..", "id": 116, "best": "00:10:23 ", "time": "00:40:45"}, {"puzzle": "8....3.7....6...9.......2...5.........7.451.....7...3...1..8.9....5......68.1.4..", "id": 117, "best": "00:10:23 ", "time": "00:40:45"}, {"puzzle": "8....3.7....6...9.......2...5.........7.451.....7...3...1..8.9....5......68.1.4..", "id": 118, "best": "00:10:23 ", "time": "00:40:45"}, {"puzzle": "8....3.7....6...9.......2...5.........7.451.....7...3...1..8.9....5......68.1.4..", "id": 119, "best": "00:10:23 ", "time": "00:40:45"}, {"puzzle": "8....3.7....6...9.......2...5.........7.451.....7...3...1..8.9....5......68.1.4..", "id": 120, "best": "00:10:23 ", "time": "00:40:45"}, {"puzzle": "8....3.7....6...9.......2...5.........7.451.....7...3...1..8.9....5......68.1.4..", "id": 121, "best": "00:10:23 ", "time": "00:40:45"}, {"puzzle": "8....3.7....6...9.......2...5.........7.451.....7...3...1..8.9....5......68.1.4..", "id": 122, "best": "00:10:23 ", "time": "00:40:45"}, {"puzzle": "8....3.7....6...9.......2...5.........7.451.....7...3...1..8.9....5......68.1.4..", "id": 123, "best": "00:10:23 ", "time": "00:40:45"}, {"puzzle": "8....3.7....6...9.......2...5.........7.451.....7...3...1..8.9....5......68.1.4..", "id": 124, "best": "00:10:23 ", "time": "00:40:45"}, {"puzzle": "8....3.7....6...9.......2...5.........7.451.....7...3...1..8.9....5......68.1.4..", "id": 125, "best": "00:10:23 ", "time": "00:40:45"}, {"puzzle": "8....3.7....6...9.......2...5.........7.451.....7...3...1..8.9....5......68.1.4..", "id": 126, "best": "00:10:23 ", "time": "00:40:45"}, {"puzzle": "8....3.7....6...9.......2...5.........7.451.....7...3...1..8.9....5......68.1.4..", "id": 127, "best": "00:10:23 ", "time": "00:40:45"}, {"puzzle": "8....3.7....6...9.......2...5.........7.451.....7...3...1..8.9....5......68.1.4..", "id": 128, "best": "00:10:23 ", "time": "00:40:45"}, {"puzzle": "8....3.7....6...9.......2...5.........7.451.....7...3...1..8.9....5......68.1.4..", "id": 129, "best": "00:10:23 ", "time": "00:40:45"}, {"puzzle": "8....3.7....6...9.......2...5.........7.451.....7...3...1..8.9....5......68.1.4..", "id": 130, "best": "00:10:23 ", "time": "00:40:45"}, {"puzzle": "8....3.7....6...9.......2...5.........7.451.....7...3...1..8.9....5......68.1.4..", "id": 131, "best": "00:10:23 ", "time": "00:40:45"}, {"puzzle": "8....3.7....6...9.......2...5.........7.451.....7...3...1..8.9....5......68.1.4..", "id": 132, "best": "00:10:23 ", "time": "00:40:45"}, {"puzzle": "8....3.7....6...9.......2...5.........7.451.....7...3...1..8.9....5......68.1.4..", "id": 133, "best": "00:10:23 ", "time": "00:40:45"}, {"puzzle": "8....3.7....6...9.......2...5.........7.451.....7...3...1..8.9....5......68.1.4..", "id": 134, "best": "00:10:23 ", "time": "00:40:45"}, {"puzzle": "8....3.7....6...9.......2...5.........7.451.....7...3...1..8.9....5......68.1.4..", "id": 135, "best": "00:10:23 ", "time": "00:40:45"}, {"puzzle": "8....3.7....6...9.......2...5.........7.451.....7...3...1..8.9....5......68.1.4..", "id": 136, "best": "00:10:23 ", "time": "00:40:45"}, {"puzzle": "8....3.7....6...9.......2...5.........7.451.....7...3...1..8.9....5......68.1.4..", "id": 137, "best": "00:10:23 ", "time": "00:40:45"}, {"puzzle": "8....3.7....6...9.......2...5.........7.451.....7...3...1..8.9....5......68.1.4..", "id": 138, "best": "00:10:23 ", "time": "00:40:45"}, {"puzzle": "8....3.7....6...9.......2...5.........7.451.....7...3...1..8.9....5......68.1.4..", "id": 139, "best": "00:10:23 ", "time": "00:40:45"}, {"puzzle": "8....3.7....6...9.......2...5.........7.451.....7...3...1..8.9....5......68.1.4..", "id": 140, "best": "00:10:23 ", "time": "00:40:45"}, {"puzzle": "8....3.7....6...9.......2...5.........7.451.....7...3...1..8.9....5......68.1.4..", "id": 141, "best": "00:10:23 ", "time": "00:40:45"}, {"puzzle": "8....3.7....6...9.......2...5.........7.451.....7...3...1..8.9....5......68.1.4..", "id": 142, "best": "00:10:23 ", "time": "00:40:45"}, {"puzzle": "8....3.7....6...9.......2...5.........7.451.....7...3...1..8.9....5......68.1.4..", "id": 143, "best": "00:10:23 ", "time": "00:40:45"}, {"puzzle": "8....3.7....6...9.......2...5.........7.451.....7...3...1..8.9....5......68.1.4..", "id": 144, "best": "00:10:23 ", "time": "00:40:45"}, {"puzzle": "8....3.7....6...9.......2...5.........7.451.....7...3...1..8.9....5......68.1.4..", "id": 145, "best": "00:10:23 ", "time": "00:40:45"}, {"puzzle": "8....3.7....6...9.......2...5.........7.451.....7...3...1..8.9....5......68.1.4..", "id": 146, "best": "00:10:23 ", "time": "00:40:45"}, {"puzzle": "8....3.7....6...9.......2...5.........7.451.....7...3...1..8.9....5......68.1.4..", "id": 147, "best": "00:10:23 ", "time": "00:40:45"}, {"puzzle": "8....3.7....6...9.......2...5.........7.451.....7...3...1..8.9....5......68.1.4..", "id": 148, "best": "00:10:23 ", "time": "00:40:45"}, {"puzzle": "8....3.7....6...9.......2...5.........7.451.....7...3...1..8.9....5......68.1.4..", "id": 149, "best": "00:10:23 ", "time": "00:40:45"}, {"puzzle": "8....3.7....6...9.......2...5.........7.451.....7...3...1..8.9....5......68.1.4..", "id": 150, "best": "00:10:23 ", "time": "00:40:45"}, {"puzzle": "8....3.7....6...9.......2...5.........7.451.....7...3...1..8.9....5......68.1.4..", "id": 151, "best": "00:10:23 ", "time": "00:40:45"}, {"puzzle": "8....3.7....6...9.......2...5.........7.451.....7...3...1..8.9....5......68.1.4..", "id": 152, "best": "00:10:23 ", "time": "00:40:45"}, {"puzzle": "8....3.7....6...9.......2...5.........7.451.....7...3...1..8.9....5......68.1.4..", "id": 153, "best": "00:10:23 ", "time": "00:40:45"}, {"puzzle": "8....3.7....6...9.......2...5.........7.451.....7...3...1..8.9....5......68.1.4..", "id": 154, "best": "00:10:23 ", "time": "00:40:45"}, {"puzzle": "8....3.7....6...9.......2...5.........7.451.....7...3...1..8.9....5......68.1.4..", "id": 155, "best": "00:10:23 ", "time": "00:40:45"}, {"puzzle": "8....3.7....6...9.......2...5.........7.451.....7...3...1..8.9....5......68.1.4..", "id": 156, "best": "00:10:23 ", "time": "00:40:45"}, {"puzzle": "8....3.7....6...9.......2...5.........7.451.....7...3...1..8.9....5......68.1.4..", "id": 157, "best": "00:10:23 ", "time": "00:40:45"}, {"puzzle": "8....3.7....6...9.......2...5.........7.451.....7...3...1..8.9....5......68.1.4..", "id": 158, "best": "00:10:23 ", "time": "00:40:45"}, {"puzzle": "8....3.7....6...9.......2...5.........7.451.....7...3...1..8.9....5......68.1.4..", "id": 159, "best": "00:10:23 ", "time": "00:40:45"}, {"puzzle": "8....3.7....6...9.......2...5.........7.451.....7...3...1..8.9....5......68.1.4..", "id": 160, "best": "00:10:23 ", "time": "00:40:45"}, {"puzzle": "8....3.7....6...9.......2...5.........7.451.....7...3...1..8.9....5......68.1.4..", "id": 161, "best": "00:10:23 ", "time": "00:40:45"}, {"puzzle": "8....3.7....6...9.......2...5.........7.451.....7...3...1..8.9....5......68.1.4..", "id": 162, "best": "00:10:23 ", "time": "00:40:45"}, {"puzzle": "8....3.7....6...9.......2...5.........7.451.....7...3...1..8.9....5......68.1.4..", "id": 163, "best": "00:10:23 ", "time": "00:40:45"}, {"puzzle": "8....3.7....6...9.......2...5.........7.451.....7...3...1..8.9....5......68.1.4..", "id": 164, "best": "00:10:23 ", "time": "00:40:45"}, {"puzzle": "8....3.7....6...9.......2...5.........7.451.....7...3...1..8.9....5......68.1.4..", "id": 165, "best": "00:10:23 ", "time": "00:40:45"}, {"puzzle": "8....3.7....6...9.......2...5.........7.451.....7...3...1..8.9....5......68.1.4..", "id": 166, "best": "00:10:23 ", "time": "00:40:45"}, {"puzzle": "8....3.7....6...9.......2...5.........7.451.....7...3...1..8.9....5......68.1.4..", "id": 167, "best": "00:10:23 ", "time": "00:40:45"}, {"puzzle": "8....3.7....6...9.......2...5.........7.451.....7...3...1..8.9....5......68.1.4..", "id": 168, "best": "00:10:23 ", "time": "00:40:45"}, {"puzzle": "8....3.7....6...9.......2...5.........7.451.....7...3...1..8.9....5......68.1.4..", "id": 169, "best": "00:10:23 ", "time": "00:40:45"}, {"puzzle": "8....3.7....6...9.......2...5.........7.451.....7...3...1..8.9....5......68.1.4..", "id": 170, "best": "00:10:23 ", "time": "00:40:45"}, {"puzzle": "8....3.7....6...9.......2...5.........7.451.....7...3...1..8.9....5......68.1.4..", "id": 171, "best": "00:10:23 ", "time": "00:40:45"}, {"puzzle": "8....3.7....6...9.......2...5.........7.451.....7...3...1..8.9....5......68.1.4..", "id": 172, "best": "00:10:23 ", "time": "00:40:45"}, {"puzzle": "8....3.7....6...9.......2...5.........7.451.....7...3...1..8.9....5......68.1.4..", "id": 173, "best": "00:10:23 ", "time": "00:40:45"}, {"puzzle": "8....3.7....6...9.......2...5.........7.451.....7...3...1..8.9....5......68.1.4..", "id": 174, "best": "00:10:23 ", "time": "00:40:45"}, {"puzzle": "8....3.7....6...9.......2...5.........7.451.....7...3...1..8.9....5......68.1.4..", "id": 175, "best": "00:10:23 ", "time": "00:40:45"}, {"puzzle": "8....3.7....6...9.......2...5.........7.451.....7...3...1..8.9....5......68.1.4..", "id": 176, "best": "00:10:23 ", "time": "00:40:45"}, {"puzzle": "8....3.7....6...9.......2...5.........7.451.....7...3...1..8.9....5......68.1.4..", "id": 177, "best": "00:10:23 ", "time": "00:40:45"}, {"puzzle": "8....3.7....6...9.......2...5.........7.451.....7...3...1..8.9....5......68.1.4..", "id": 178, "best": "00:10:23 ", "time": "00:40:45"}, {"puzzle": "8....3.7....6...9.......2...5.........7.451.....7...3...1..8.9....5......68.1.4..", "id": 179, "best": "00:10:23 ", "time": "00:40:45"}, {"puzzle": "8....3.7....6...9.......2...5.........7.451.....7...3...1..8.9....5......68.1.4..", "id": 180, "best": "00:10:23 ", "time": "00:40:45"}, {"puzzle": "8....3.7....6...9.......2...5.........7.451.....7...3...1..8.9....5......68.1.4..", "id": 181, "best": "00:10:23 ", "time": "00:40:45"}, {"puzzle": "8....3.7....6...9.......2...5.........7.451.....7...3...1..8.9....5......68.1.4..", "id": 182, "best": "00:10:23 ", "time": "00:40:45"}, {"puzzle": "8....3.7....6...9.......2...5.........7.451.....7...3...1..8.9....5......68.1.4..", "id": 183, "best": "00:10:23 ", "time": "00:40:45"}, {"puzzle": "8....3.7....6...9.......2...5.........7.451.....7...3...1..8.9....5......68.1.4..", "id": 184, "best": "00:10:23 ", "time": "00:40:45"}, {"puzzle": "8....3.7....6...9.......2...5.........7.451.....7...3...1..8.9....5......68.1.4..", "id": 185, "best": "00:10:23 ", "time": "00:40:45"}, {"puzzle": "8....3.7....6...9.......2...5.........7.451.....7...3...1..8.9....5......68.1.4..", "id": 186, "best": "00:10:23 ", "time": "00:40:45"}, {"puzzle": "8....3.7....6...9.......2...5.........7.451.....7...3...1..8.9....5......68.1.4..", "id": 187, "best": "00:10:23 ", "time": "00:40:45"}, {"puzzle": "8....3.7....6...9.......2...5.........7.451.....7...3...1..8.9....5......68.1.4..", "id": 188, "best": "00:10:23 ", "time": "00:40:45"}, {"puzzle": "8....3.7....6...9.......2...5.........7.451.....7...3...1..8.9....5......68.1.4..", "id": 189, "best": "00:10:23 ", "time": "00:40:45"}, {"puzzle": "8....3.7....6...9.......2...5.........7.451.....7...3...1..8.9....5......68.1.4..", "id": 190, "best": "00:10:23 ", "time": "00:40:45"}, {"puzzle": "8....3.7....6...9.......2...5.........7.451.....7...3...1..8.9....5......68.1.4..", "id": 191, "best": "00:10:23 ", "time": "00:40:45"}, {"puzzle": "8....3.7....6...9.......2...5.........7.451.....7...3...1..8.9....5......68.1.4..", "id": 192, "best": "00:10:23 ", "time": "00:40:45"}, {"puzzle": "8....3.7....6...9.......2...5.........7.451.....7...3...1..8.9....5......68.1.4..", "id": 193, "best": "00:10:23 ", "time": "00:40:45"}, {"puzzle": "8....3.7....6...9.......2...5.........7.451.....7...3...1..8.9....5......68.1.4..", "id": 194, "best": "00:10:23 ", "time": "00:40:45"}, {"puzzle": "8....3.7....6...9.......2...5.........7.451.....7...3...1..8.9....5......68.1.4..", "id": 195, "best": "00:10:23 ", "time": "00:40:45"}, {"puzzle": "8....3.7....6...9.......2...5.........7.451.....7...3...1..8.9....5......68.1.4..", "id": 196, "best": "00:10:23 ", "time": "00:40:45"}, {"puzzle": "8....3.7....6...9.......2...5.........7.451.....7...3...1..8.9....5......68.1.4..", "id": 197, "best": "00:10:23 ", "time": "00:40:45"}, {"puzzle": "8....3.7....6...9.......2...5.........7.451.....7...3...1..8.9....5......68.1.4..", "id": 198, "best": "00:10:23 ", "time": "00:40:45"}, {"puzzle": "8....3.7....6...9.......2...5.........7.451.....7...3...1..8.9....5......68.1.4..", "id": 199, "best": "00:10:23 ", "time": "00:40:45"}, {"puzzle": "8....3.7....6...9.......2...5.........7.451.....7...3...1..8.9....5......68.1.4..", "id": 200, "best": "00:10:23 ", "time": "00:40:45"}, {"puzzle": "8....3.7....6...9.......2...5.........7.451.....7...3...1..8.9....5......68.1.4..", "id": 201, "best": "00:10:23 ", "time": "00:40:45"}, {"puzzle": "8....3.7....6...9.......2...5.........7.451.....7...3...1..8.9....5......68.1.4..", "id": 202, "best": "00:10:23 ", "time": "00:40:45"}, {"puzzle": "8....3.7....6...9.......2...5.........7.451.....7...3...1..8.9....5......68.1.4..", "id": 203, "best": "00:10:23 ", "time": "00:40:45"}, {"puzzle": "8....3.7....6...9.......2...5.........7.451.....7...3...1..8.9....5......68.1.4..", "id": 204, "best": "00:10:23 ", "time": "00:40:45"}, {"puzzle": "8....3.7....6...9.......2...5.........7.451.....7...3...1..8.9....5......68.1.4..", "id": 205, "best": "00:10:23 ", "time": "00:40:45"}, {"puzzle": "8....3.7....6...9.......2...5.........7.451.....7...3...1..8.9....5......68.1.4..", "id": 206, "best": "00:10:23 ", "time": "00:40:45"}, {"puzzle": "8....3.7....6...9.......2...5.........7.451.....7...3...1..8.9....5......68.1.4..", "id": 207, "best": "00:10:23 ", "time": "00:40:45"}, {"puzzle": "8....3.7....6...9.......2...5.........7.451.....7...3...1..8.9....5......68.1.4..", "id": 208, "best": "00:10:23 ", "time": "00:40:45"}, {"puzzle": "8....3.7....6...9.......2...5.........7.451.....7...3...1..8.9....5......68.1.4..", "id": 209, "best": "00:10:23 ", "time": "00:40:45"}, {"puzzle": "8....3.7....6...9.......2...5.........7.451.....7...3...1..8.9....5......68.1.4..", "id": 210, "best": "00:10:23 ", "time": "00:40:45"}, {"puzzle": "8....3.7....6...9.......2...5.........7.451.....7...3...1..8.9....5......68.1.4..", "id": 211, "best": "00:10:23 ", "time": "00:40:45"}, {"puzzle": "8....3.7....6...9.......2...5.........7.451.....7...3...1..8.9....5......68.1.4..", "id": 212, "best": "00:10:23 ", "time": "00:40:45"}, {"puzzle": "8....3.7....6...9.......2...5.........7.451.....7...3...1..8.9....5......68.1.4..", "id": 213, "best": "00:10:23 ", "time": "00:40:45"}, {"puzzle": "8....3.7....6...9.......2...5.........7.451.....7...3...1..8.9....5......68.1.4..", "id": 214, "best": "00:10:23 ", "time": "00:40:45"}, {"puzzle": "8....3.7....6...9.......2...5.........7.451.....7...3...1..8.9....5......68.1.4..", "id": 215, "best": "00:10:23 ", "time": "00:40:45"}, {"puzzle": "8....3.7....6...9.......2...5.........7.451.....7...3...1..8.9....5......68.1.4..", "id": 216, "best": "00:10:23 ", "time": "00:40:45"}, {"puzzle": "8....3.7....6...9.......2...5.........7.451.....7...3...1..8.9....5......68.1.4..", "id": 217, "best": "00:10:23 ", "time": "00:40:45"}, {"puzzle": "8....3.7....6...9.......2...5.........7.451.....7...3...1..8.9....5......68.1.4..", "id": 218, "best": "00:10:23 ", "time": "00:40:45"}, {"puzzle": "8....3.7....6...9.......2...5.........7.451.....7...3...1..8.9....5......68.1.4..", "id": 219, "best": "00:10:23 ", "time": "00:40:45"}, {"puzzle": "8....3.7....6...9.......2...5.........7.451.....7...3...1..8.9....5......68.1.4..", "id": 220, "best": "00:10:23 ", "time": "00:40:45"}, {"puzzle": "8....3.7....6...9.......2...5.........7.451.....7...3...1..8.9....5......68.1.4..", "id": 221, "best": "00:10:23 ", "time": "00:40:45"}, {"puzzle": "8....3.7....6...9.......2...5.........7.451.....7...3...1..8.9....5......68.1.4..", "id": 222, "best": "00:10:23 ", "time": "00:40:45"}, {"puzzle": "8....3.7....6...9.......2...5.........7.451.....7...3...1..8.9....5......68.1.4..", "id": 223, "best": "00:10:23 ", "time": "00:40:45"}, {"puzzle": "8....3.7....6...9.......2...5.........7.451.....7...3...1..8.9....5......68.1.4..", "id": 224, "best": "00:10:23 ", "time": "00:40:45"}, {"puzzle": "8....3.7....6...9.......2...5.........7.451.....7...3...1..8.9....5......68.1.4..", "id": 225, "best": "00:10:23 ", "time": "00:40:45"}, {"puzzle": "8....3.7....6...9.......2...5.........7.451.....7...3...1..8.9....5......68.1.4..", "id": 226, "best": "00:10:23 ", "time": "00:40:45"}, {"puzzle": "8....3.7....6...9.......2...5.........7.451.....7...3...1..8.9....5......68.1.4..", "id": 227, "best": "00:10:23 ", "time": "00:40:45"}, {"puzzle": "8....3.7....6...9.......2...5.........7.451.....7...3...1..8.9....5......68.1.4..", "id": 228, "best": "00:10:23 ", "time": "00:40:45"}, {"puzzle": "8....3.7....6...9.......2...5.........7.451.....7...3...1..8.9....5......68.1.4..", "id": 229, "best": "00:10:23 ", "time": "00:40:45"}, {"puzzle": "8....3.7....6...9.......2...5.........7.451.....7...3...1..8.9....5......68.1.4..", "id": 230, "best": "00:10:23 ", "time": "00:40:45"}, {"puzzle": "8....3.7....6...9.......2...5.........7.451.....7...3...1..8.9....5......68.1.4..", "id": 231, "best": "00:10:23 ", "time": "00:40:45"}, {"puzzle": "8....3.7....6...9.......2...5.........7.451.....7...3...1..8.9....5......68.1.4..", "id": 232, "best": "00:10:23 ", "time": "00:40:45"}, {"puzzle": "8....3.7....6...9.......2...5.........7.451.....7...3...1..8.9....5......68.1.4..", "id": 233, "best": "00:10:23 ", "time": "00:40:45"}, {"puzzle": "8....3.7....6...9.......2...5.........7.451.....7...3...1..8.9....5......68.1.4..", "id": 234, "best": "00:10:23 ", "time": "00:40:45"}, {"puzzle": "8....3.7....6...9.......2...5.........7.451.....7...3...1..8.9....5......68.1.4..", "id": 235, "best": "00:10:23 ", "time": "00:40:45"}, {"puzzle": "8....3.7....6...9.......2...5.........7.451.....7...3...1..8.9....5......68.1.4..", "id": 236, "best": "00:10:23 ", "time": "00:40:45"}, {"puzzle": "8....3.7....6...9.......2...5.........7.451.....7...3...1..8.9....5......68.1.4..", "id": 237, "best": "00:10:23 ", "time": "00:40:45"}, {"puzzle": "8....3.7....6...9.......2...5.........7.451.....7...3...1..8.9....5......68.1.4..", "id": 238, "best": "00:10:23 ", "time": "00:40:45"}, {"puzzle": "8....3.7....6...9.......2...5.........7.451.....7...3...1..8.9....5......68.1.4..", "id": 239, "best": "00:10:23 ", "time": "00:40:45"}, {"puzzle": "8....3.7....6...9.......2...5.........7.451.....7...3...1..8.9....5......68.1.4..", "id": 240, "best": "00:10:23 ", "time": "00:40:45"}, {"puzzle": "8....3.7....6...9.......2...5.........7.451.....7...3...1..8.9....5......68.1.4..", "id": 241, "best": "00:10:23 ", "time": "00:40:45"}, {"puzzle": "8....3.7....6...9.......2...5.........7.451.....7...3...1..8.9....5......68.1.4..", "id": 242, "best": "00:10:23 ", "time": "00:40:45"}, {"puzzle": "8....3.7....6...9.......2...5.........7.451.....7...3...1..8.9....5......68.1.4..", "id": 243, "best": "00:10:23 ", "time": "00:40:45"}, {"puzzle": "8....3.7....6...9.......2...5.........7.451.....7...3...1..8.9....5......68.1.4..", "id": 244, "best": "00:10:23 ", "time": "00:40:45"}, {"puzzle": "8....3.7....6...9.......2...5.........7.451.....7...3...1..8.9....5......68.1.4..", "id": 245, "best": "00:10:23 ", "time": "00:40:45"}, {"puzzle": "8....3.7....6...9.......2...5.........7.451.....7...3...1..8.9....5......68.1.4..", "id": 246, "best": "00:10:23 ", "time": "00:40:45"}, {"puzzle": "8....3.7....6...9.......2...5.........7.451.....7...3...1..8.9....5......68.1.4..", "id": 247, "best": "00:10:23 ", "time": "00:40:45"}, {"puzzle": "8....3.7....6...9.......2...5.........7.451.....7...3...1..8.9....5......68.1.4..", "id": 248, "best": "00:10:23 ", "time": "00:40:45"}, {"puzzle": "8....3.7....6...9.......2...5.........7.451.....7...3...1..8.9....5......68.1.4..", "id": 249, "best": "00:10:23 ", "time": "00:40:45"}, {"puzzle": "8....3.7....6...9.......2...5.........7.451.....7...3...1..8.9....5......68.1.4..", "id": 250, "best": "00:10:23 ", "time": "00:40:45"}, {"puzzle": "8....3.7....6...9.......2...5.........7.451.....7...3...1..8.9....5......68.1.4..", "id": 251, "best": "00:10:23 ", "time": "00:40:45"}, {"puzzle": "8....3.7....6...9.......2...5.........7.451.....7...3...1..8.9....5......68.1.4..", "id": 252, "best": "00:10:23 ", "time": "00:40:45"}, {"puzzle": "8....3.7....6...9.......2...5.........7.451.....7...3...1..8.9....5......68.1.4..", "id": 253, "best": "00:10:23 ", "time": "00:40:45"}, {"puzzle": "8....3.7....6...9.......2...5.........7.451.....7...3...1..8.9....5......68.1.4..", "id": 254, "best": "00:10:23 ", "time": "00:40:45"}, {"puzzle": "8....3.7....6...9.......2...5.........7.451.....7...3...1..8.9....5......68.1.4..", "id": 255, "best": "00:10:23 ", "time": "00:40:45"}, {"puzzle": "8....3.7....6...9.......2...5.........7.451.....7...3...1..8.9....5......68.1.4..", "id": 256, "best": "00:10:23 ", "time": "00:40:45"}, {"puzzle": "8....3.7....6...9.......2...5.........7.451.....7...3...1..8.9....5......68.1.4..", "id": 257, "best": "00:10:23 ", "time": "00:40:45"}, {"puzzle": "8....3.7....6...9.......2...5.........7.451.....7...3...1..8.9....5......68.1.4..", "id": 258, "best": "00:10:23 ", "time": "00:40:45"}, {"puzzle": "8....3.7....6...9.......2...5.........7.451.....7...3...1..8.9....5......68.1.4..", "id": 259, "best": "00:10:23 ", "time": "00:40:45"}, {"puzzle": "8....3.7....6...9.......2...5.........7.451.....7...3...1..8.9....5......68.1.4..", "id": 260, "best": "00:10:23 ", "time": "00:40:45"}, {"puzzle": "8....3.7....6...9.......2...5.........7.451.....7...3...1..8.9....5......68.1.4..", "id": 261, "best": "00:10:23 ", "time": "00:40:45"}, {"puzzle": "8....3.7....6...9.......2...5.........7.451.....7...3...1..8.9....5......68.1.4..", "id": 262, "best": "00:10:23 ", "time": "00:40:45"}, {"puzzle": "8....3.7....6...9.......2...5.........7.451.....7...3...1..8.9....5......68.1.4..", "id": 263, "best": "00:10:23 ", "time": "00:40:45"}, {"puzzle": "8....3.7....6...9.......2...5.........7.451.....7...3...1..8.9....5......68.1.4..", "id": 264, "best": "00:10:23 ", "time": "00:40:45"}, {"puzzle": "8....3.7....6...9.......2...5.........7.451.....7...3...1..8.9....5......68.1.4..", "id": 265, "best": "00:10:23 ", "time": "00:40:45"}, {"puzzle": "8....3.7....6...9.......2...5.........7.451.....7...3...1..8.9....5......68.1.4..", "id": 266, "best": "00:10:23 ", "time": "00:40:45"}, {"puzzle": "8....3.7....6...9.......2...5.........7.451.....7...3...1..8.9....5......68.1.4..", "id": 267, "best": "00:10:23 ", "time": "00:40:45"}, {"puzzle": "8....3.7....6...9.......2...5.........7.451.....7...3...1..8.9....5......68.1.4..", "id": 268, "best": "00:10:23 ", "time": "00:40:45"}, {"puzzle": "8....3.7....6...9.......2...5.........7.451.....7...3...1..8.9....5......68.1.4..", "id": 269, "best": "00:10:23 ", "time": "00:40:45"}, {"puzzle": "8....3.7....6...9.......2...5.........7.451.....7...3...1..8.9....5......68.1.4..", "id": 270, "best": "00:10:23 ", "time": "00:40:45"}, {"puzzle": "8....3.7....6...9.......2...5.........7.451.....7...3...1..8.9....5......68.1.4..", "id": 271, "best": "00:10:23 ", "time": "00:40:45"}, {"puzzle": "8....3.7....6...9.......2...5.........7.451.....7...3...1..8.9....5......68.1.4..", "id": 272, "best": "00:10:23 ", "time": "00:40:45"}, {"puzzle": "8....3.7....6...9.......2...5.........7.451.....7...3...1..8.9....5......68.1.4..", "id": 273, "best": "00:10:23 ", "time": "00:40:45"}, {"puzzle": "8....3.7....6...9.......2...5.........7.451.....7...3...1..8.9....5......68.1.4..", "id": 274, "best": "00:10:23 ", "time": "00:40:45"}, {"puzzle": "8....3.7....6...9.......2...5.........7.451.....7...3...1..8.9....5......68.1.4..", "id": 275, "best": "00:10:23 ", "time": "00:40:45"}, {"puzzle": "8....3.7....6...9.......2...5.........7.451.....7...3...1..8.9....5......68.1.4..", "id": 276, "best": "00:10:23 ", "time": "00:40:45"}, {"puzzle": "8....3.7....6...9.......2...5.........7.451.....7...3...1..8.9....5......68.1.4..", "id": 277, "best": "00:10:23 ", "time": "00:40:45"}, {"puzzle": "8....3.7....6...9.......2...5.........7.451.....7...3...1..8.9....5......68.1.4..", "id": 278, "best": "00:10:23 ", "time": "00:40:45"}, {"puzzle": "8....3.7....6...9.......2...5.........7.451.....7...3...1..8.9....5......68.1.4..", "id": 279, "best": "00:10:23 ", "time": "00:40:45"}, {"puzzle": "8....3.7....6...9.......2...5.........7.451.....7...3...1..8.9....5......68.1.4..", "id": 280, "best": "00:10:23 ", "time": "00:40:45"}, {"puzzle": "8....3.7....6...9.......2...5.........7.451.....7...3...1..8.9....5......68.1.4..", "id": 281, "best": "00:10:23 ", "time": "00:40:45"}, {"puzzle": "8....3.7....6...9.......2...5.........7.451.....7...3...1..8.9....5......68.1.4..", "id": 282, "best": "00:10:23 ", "time": "00:40:45"}, {"puzzle": "8....3.7....6...9.......2...5.........7.451.....7...3...1..8.9....5......68.1.4..", "id": 283, "best": "00:10:23 ", "time": "00:40:45"}, {"puzzle": "8....3.7....6...9.......2...5.........7.451.....7...3...1..8.9....5......68.1.4..", "id": 284, "best": "00:10:23 ", "time": "00:40:45"}, {"puzzle": "8....3.7....6...9.......2...5.........7.451.....7...3...1..8.9....5......68.1.4..", "id": 285, "best": "00:10:23 ", "time": "00:40:45"}, {"puzzle": "8....3.7....6...9.......2...5.........7.451.....7...3...1..8.9....5......68.1.4..", "id": 286, "best": "00:10:23 ", "time": "00:40:45"}, {"puzzle": "8....3.7....6...9.......2...5.........7.451.....7...3...1..8.9....5......68.1.4..", "id": 287, "best": "00:10:23 ", "time": "00:40:45"}, {"puzzle": "8....3.7....6...9.......2...5.........7.451.....7...3...1..8.9....5......68.1.4..", "id": 288, "best": "00:10:23 ", "time": "00:40:45"}, {"puzzle": "8....3.7....6...9.......2...5.........7.451.....7...3...1..8.9....5......68.1.4..", "id": 289, "best": "00:10:23 ", "time": "00:40:45"}, {"puzzle": "8....3.7....6...9.......2...5.........7.451.....7...3...1..8.9....5......68.1.4..", "id": 290, "best": "00:10:23 ", "time": "00:40:45"}, {"puzzle": "8....3.7....6...9.......2...5.........7.451.....7...3...1..8.9....5......68.1.4..", "id": 291, "best": "00:10:23 ", "time": "00:40:45"}, {"puzzle": "8....3.7....6...9.......2...5.........7.451.....7...3...1..8.9....5......68.1.4..", "id": 292, "best": "00:10:23 ", "time": "00:40:45"}, {"puzzle": "8....3.7....6...9.......2...5.........7.451.....7...3...1..8.9....5......68.1.4..", "id": 293, "best": "00:10:23 ", "time": "00:40:45"}, {"puzzle": "8....3.7....6...9.......2...5.........7.451.....7...3...1..8.9....5......68.1.4..", "id": 294, "best": "00:10:23 ", "time": "00:40:45"}, {"puzzle": "8....3.7....6...9.......2...5.........7.451.....7...3...1..8.9....5......68.1.4..", "id": 295, "best": "00:10:23 ", "time": "00:40:45"}, {"puzzle": "8....3.7....6...9.......2...5.........7.451.....7...3...1..8.9....5......68.1.4..", "id": 296, "best": "00:10:23 ", "time": "00:40:45"}, {"puzzle": "8....3.7....6...9.......2...5.........7.451.....7...3...1..8.9....5......68.1.4..", "id": 297, "best": "00:10:23 ", "time": "00:40:45"}, {"puzzle": "8....3.7....6...9.......2...5.........7.451.....7...3...1..8.9....5......68.1.4..", "id": 298, "best": "00:10:23 ", "time": "00:40:45"}, {"puzzle": "8....3.7....6...9.......2...5.........7.451.....7...3...1..8.9....5......68.1.4..", "id": 299, "best": "00:10:23 ", "time": "00:40:45"}, {"puzzle": "8....3.7....6...9.......2...5.........7.451.....7...3...1..8.9....5......68.1.4..", "id": 300, "best": "00:10:23 ", "time": "00:40:45"}, {"puzzle": "8....3.7....6...9.......2...5.........7.451.....7...3...1..8.9....5......68.1.4..", "id": 301, "best": "00:10:23 ", "time": "00:40:45"}, {"puzzle": "8....3.7....6...9.......2...5.........7.451.....7...3...1..8.9....5......68.1.4..", "id": 302, "best": "00:10:23 ", "time": "00:40:45"}, {"puzzle": "8....3.7....6...9.......2...5.........7.451.....7...3...1..8.9....5......68.1.4..", "id": 303, "best": "00:10:23 ", "time": "00:40:45"}, {"puzzle": "8....3.7....6...9.......2...5.........7.451.....7...3...1..8.9....5......68.1.4..", "id": 304, "best": "00:10:23 ", "time": "00:40:45"}, {"puzzle": "8....3.7....6...9.......2...5.........7.451.....7...3...1..8.9....5......68.1.4..", "id": 305, "best": "00:10:23 ", "time": "00:40:45"}, {"puzzle": "8....3.7....6...9.......2...5.........7.451.....7...3...1..8.9....5......68.1.4..", "id": 306, "best": "00:10:23 ", "time": "00:40:45"}, {"puzzle": "8....3.7....6...9.......2...5.........7.451.....7...3...1..8.9....5......68.1.4..", "id": 307, "best": "00:10:23 ", "time": "00:40:45"}, {"puzzle": "8....3.7....6...9.......2...5.........7.451.....7...3...1..8.9....5......68.1.4..", "id": 308, "best": "00:10:23 ", "time": "00:40:45"}, {"puzzle": "8....3.7....6...9.......2...5.........7.451.....7...3...1..8.9....5......68.1.4..", "id": 309, "best": "00:10:23 ", "time": "00:40:45"}, {"puzzle": "8....3.7....6...9.......2...5.........7.451.....7...3...1..8.9....5......68.1.4..", "id": 310, "best": "00:10:23 ", "time": "00:40:45"}, {"puzzle": "8....3.7....6...9.......2...5.........7.451.....7...3...1..8.9....5......68.1.4..", "id": 311, "best": "00:10:23 ", "time": "00:40:45"}, {"puzzle": "8....3.7....6...9.......2...5.........7.451.....7...3...1..8.9....5......68.1.4..", "id": 312, "best": "00:10:23 ", "time": "00:40:45"}, {"puzzle": "8....3.7....6...9.......2...5.........7.451.....7...3...1..8.9....5......68.1.4..", "id": 313, "best": "00:10:23 ", "time": "00:40:45"}, {"puzzle": "8....3.7....6...9.......2...5.........7.451.....7...3...1..8.9....5......68.1.4..", "id": 314, "best": "00:10:23 ", "time": "00:40:45"}, {"puzzle": "8....3.7....6...9.......2...5.........7.451.....7...3...1..8.9....5......68.1.4..", "id": 315, "best": "00:10:23 ", "time": "00:40:45"}, {"puzzle": "8....3.7....6...9.......2...5.........7.451.....7...3...1..8.9....5......68.1.4..", "id": 316, "best": "00:10:23 ", "time": "00:40:45"}, {"puzzle": "8....3.7....6...9.......2...5.........7.451.....7...3...1..8.9....5......68.1.4..", "id": 317, "best": "00:10:23 ", "time": "00:40:45"}, {"puzzle": "8....3.7....6...9.......2...5.........7.451.....7...3...1..8.9....5......68.1.4..", "id": 318, "best": "00:10:23 ", "time": "00:40:45"}, {"puzzle": "8....3.7....6...9.......2...5.........7.451.....7...3...1..8.9....5......68.1.4..", "id": 319, "best": "00:10:23 ", "time": "00:40:45"}, {"puzzle": "8....3.7....6...9.......2...5.........7.451.....7...3...1..8.9....5......68.1.4..", "id": 320, "best": "00:10:23 ", "time": "00:40:45"}, {"puzzle": "8....3.7....6...9.......2...5.........7.451.....7...3...1..8.9....5......68.1.4..", "id": 321, "best": "00:10:23 ", "time": "00:40:45"}, {"puzzle": "8....3.7....6...9.......2...5.........7.451.....7...3...1..8.9....5......68.1.4..", "id": 322, "best": "00:10:23 ", "time": "00:40:45"}, {"puzzle": "8....3.7....6...9.......2...5.........7.451.....7...3...1..8.9....5......68.1.4..", "id": 323, "best": "00:10:23 ", "time": "00:40:45"}, {"puzzle": "8....3.7....6...9.......2...5.........7.451.....7...3...1..8.9....5......68.1.4..", "id": 324, "best": "00:10:23 ", "time": "00:40:45"}, {"puzzle": "8....3.7....6...9.......2...5.........7.451.....7...3...1..8.9....5......68.1.4..", "id": 325, "best": "00:10:23 ", "time": "00:40:45"}, {"puzzle": "8....3.7....6...9.......2...5.........7.451.....7...3...1..8.9....5......68.1.4..", "id": 326, "best": "00:10:23 ", "time": "00:40:45"}, {"puzzle": "8....3.7....6...9.......2...5.........7.451.....7...3...1..8.9....5......68.1.4..", "id": 327, "best": "00:10:23 ", "time": "00:40:45"}, {"puzzle": "8....3.7....6...9.......2...5.........7.451.....7...3...1..8.9....5......68.1.4..", "id": 328, "best": "00:10:23 ", "time": "00:40:45"}, {"puzzle": "8....3.7....6...9.......2...5.........7.451.....7...3...1..8.9....5......68.1.4..", "id": 329, "best": "00:10:23 ", "time": "00:40:45"}, {"puzzle": "8....3.7....6...9.......2...5.........7.451.....7...3...1..8.9....5......68.1.4..", "id": 330, "best": "00:10:23 ", "time": "00:40:45"}, {"puzzle": "8....3.7....6...9.......2...5.........7.451.....7...3...1..8.9....5......68.1.4..", "id": 331, "best": "00:10:23 ", "time": "00:40:45"}, {"puzzle": "8....3.7....6...9.......2...5.........7.451.....7...3...1..8.9....5......68.1.4..", "id": 332, "best": "00:10:23 ", "time": "00:40:45"}, {"puzzle": "8....3.7....6...9.......2...5.........7.451.....7...3...1..8.9....5......68.1.4..", "id": 333, "best": "00:10:23 ", "time": "00:40:45"}, {"puzzle": "8....3.7....6...9.......2...5.........7.451.....7...3...1..8.9....5......68.1.4..", "id": 334, "best": "00:10:23 ", "time": "00:40:45"}, {"puzzle": "8....3.7....6...9.......2...5.........7.451.....7...3...1..8.9....5......68.1.4..", "id": 335, "best": "00:10:23 ", "time": "00:40:45"}, {"puzzle": "8....3.7....6...9.......2...5.........7.451.....7...3...1..8.9....5......68.1.4..", "id": 336, "best": "00:10:23 ", "time": "00:40:45"}, {"puzzle": "8....3.7....6...9.......2...5.........7.451.....7...3...1..8.9....5......68.1.4..", "id": 337, "best": "00:10:23 ", "time": "00:40:45"}, {"puzzle": "8....3.7....6...9.......2...5.........7.451.....7...3...1..8.9....5......68.1.4..", "id": 338, "best": "00:10:23 ", "time": "00:40:45"}, {"puzzle": "8....3.7....6...9.......2...5.........7.451.....7...3...1..8.9....5......68.1.4..", "id": 339, "best": "00:10:23 ", "time": "00:40:45"}, {"puzzle": "8....3.7....6...9.......2...5.........7.451.....7...3...1..8.9....5......68.1.4..", "id": 340, "best": "00:10:23 ", "time": "00:40:45"}, {"puzzle": "8....3.7....6...9.......2...5.........7.451.....7...3...1..8.9....5......68.1.4..", "id": 341, "best": "00:10:23 ", "time": "00:40:45"}, {"puzzle": "8....3.7....6...9.......2...5.........7.451.....7...3...1..8.9....5......68.1.4..", "id": 342, "best": "00:10:23 ", "time": "00:40:45"}, {"puzzle": "8....3.7....6...9.......2...5.........7.451.....7...3...1..8.9....5......68.1.4..", "id": 343, "best": "00:10:23 ", "time": "00:40:45"}, {"puzzle": "8....3.7....6...9.......2...5.........7.451.....7...3...1..8.9....5......68.1.4..", "id": 344, "best": "00:10:23 ", "time": "00:40:45"}, {"puzzle": "8....3.7....6...9.......2...5.........7.451.....7...3...1..8.9....5......68.1.4..", "id": 345, "best": "00:10:23 ", "time": "00:40:45"}, {"puzzle": "8....3.7....6...9.......2...5.........7.451.....7...3...1..8.9....5......68.1.4..", "id": 346, "best": "00:10:23 ", "time": "00:40:45"}, {"puzzle": "8....3.7....6...9.......2...5.........7.451.....7...3...1..8.9....5......68.1.4..", "id": 347, "best": "00:10:23 ", "time": "00:40:45"}, {"puzzle": "8....3.7....6...9.......2...5.........7.451.....7...3...1..8.9....5......68.1.4..", "id": 348, "best": "00:10:23 ", "time": "00:40:45"}, {"puzzle": "8....3.7....6...9.......2...5.........7.451.....7...3...1..8.9....5......68.1.4..", "id": 349, "best": "00:10:23 ", "time": "00:40:45"}, {"puzzle": "8....3.7....6...9.......2...5.........7.451.....7...3...1..8.9....5......68.1.4..", "id": 350, "best": "00:10:23 ", "time": "00:40:45"}, {"puzzle": "8....3.7....6...9.......2...5.........7.451.....7...3...1..8.9....5......68.1.4..", "id": 351, "best": "00:10:23 ", "time": "00:40:45"}, {"puzzle": "8....3.7....6...9.......2...5.........7.451.....7...3...1..8.9....5......68.1.4..", "id": 352, "best": "00:10:23 ", "time": "00:40:45"}, {"puzzle": "8....3.7....6...9.......2...5.........7.451.....7...3...1..8.9....5......68.1.4..", "id": 353, "best": "00:10:23 ", "time": "00:40:45"}, {"puzzle": "8....3.7....6...9.......2...5.........7.451.....7...3...1..8.9....5......68.1.4..", "id": 354, "best": "00:10:23 ", "time": "00:40:45"}, {"puzzle": "8....3.7....6...9.......2...5.........7.451.....7...3...1..8.9....5......68.1.4..", "id": 355, "best": "00:10:23 ", "time": "00:40:45"}, {"puzzle": "8....3.7....6...9.......2...5.........7.451.....7...3...1..8.9....5......68.1.4..", "id": 356, "best": "00:10:23 ", "time": "00:40:45"}, {"puzzle": "8....3.7....6...9.......2...5.........7.451.....7...3...1..8.9....5......68.1.4..", "id": 357, "best": "00:10:23 ", "time": "00:40:45"}, {"puzzle": "8....3.7....6...9.......2...5.........7.451.....7...3...1..8.9....5......68.1.4..", "id": 358, "best": "00:10:23 ", "time": "00:40:45"}, {"puzzle": "8....3.7....6...9.......2...5.........7.451.....7...3...1..8.9....5......68.1.4..", "id": 359, "best": "00:10:23 ", "time": "00:40:45"}, {"puzzle": "8....3.7....6...9.......2...5.........7.451.....7...3...1..8.9....5......68.1.4..", "id": 360, "best": "00:10:23 ", "time": "00:40:45"}, {"puzzle": "8....3.7....6...9.......2...5.........7.451.....7...3...1..8.9....5......68.1.4..", "id": 361, "best": "00:10:23 ", "time": "00:40:45"}, {"puzzle": "8....3.7....6...9.......2...5.........7.451.....7...3...1..8.9....5......68.1.4..", "id": 362, "best": "00:10:23 ", "time": "00:40:45"}, {"puzzle": "8....3.7....6...9.......2...5.........7.451.....7...3...1..8.9....5......68.1.4..", "id": 363, "best": "00:10:23 ", "time": "00:40:45"}, {"puzzle": "8....3.7....6...9.......2...5.........7.451.....7...3...1..8.9....5......68.1.4..", "id": 364, "best": "00:10:23 ", "time": "00:40:45"}, {"puzzle": "8....3.7....6...9.......2...5.........7.451.....7...3...1..8.9....5......68.1.4..", "id": 365, "best": "00:10:23 ", "time": "00:40:45"}, {"puzzle": "8....3.7....6...9.......2...5.........7.451.....7...3...1..8.9....5......68.1.4..", "id": 366, "best": "00:10:23 ", "time": "00:40:45"}, {"puzzle": "8....3.7....6...9.......2...5.........7.451.....7...3...1..8.9....5......68.1.4..", "id": 367, "best": "00:10:23 ", "time": "00:40:45"}, {"puzzle": "8....3.7....6...9.......2...5.........7.451.....7...3...1..8.9....5......68.1.4..", "id": 368, "best": "00:10:23 ", "time": "00:40:45"}, {"puzzle": "8....3.7....6...9.......2...5.........7.451.....7...3...1..8.9....5......68.1.4..", "id": 369, "best": "00:10:23 ", "time": "00:40:45"}, {"puzzle": "8....3.7....6...9.......2...5.........7.451.....7...3...1..8.9....5......68.1.4..", "id": 370, "best": "00:10:23 ", "time": "00:40:45"}, {"puzzle": "8....3.7....6...9.......2...5.........7.451.....7...3...1..8.9....5......68.1.4..", "id": 371, "best": "00:10:23 ", "time": "00:40:45"}, {"puzzle": "8....3.7....6...9.......2...5.........7.451.....7...3...1..8.9....5......68.1.4..", "id": 372, "best": "00:10:23 ", "time": "00:40:45"}, {"puzzle": "8....3.7....6...9.......2...5.........7.451.....7...3...1..8.9....5......68.1.4..", "id": 373, "best": "00:10:23 ", "time": "00:40:45"}, {"puzzle": "8....3.7....6...9.......2...5.........7.451.....7...3...1..8.9....5......68.1.4..", "id": 374, "best": "00:10:23 ", "time": "00:40:45"}, {"puzzle": "8....3.7....6...9.......2...5.........7.451.....7...3...1..8.9....5......68.1.4..", "id": 375, "best": "00:10:23 ", "time": "00:40:45"}, {"puzzle": "8....3.7....6...9.......2...5.........7.451.....7...3...1..8.9....5......68.1.4..", "id": 376, "best": "00:10:23 ", "time": "00:40:45"}, {"puzzle": "8....3.7....6...9.......2...5.........7.451.....7...3...1..8.9....5......68.1.4..", "id": 377, "best": "00:10:23 ", "time": "00:40:45"}, {"puzzle": "8....3.7....6...9.......2...5.........7.451.....7...3...1..8.9....5......68.1.4..", "id": 378, "best": "00:10:23 ", "time": "00:40:45"}, {"puzzle": "8....3.7....6...9.......2...5.........7.451.....7...3...1..8.9....5......68.1.4..", "id": 379, "best": "00:10:23 ", "time": "00:40:45"}, {"puzzle": "8....3.7....6...9.......2...5.........7.451.....7...3...1..8.9....5......68.1.4..", "id": 380, "best": "00:10:23 ", "time": "00:40:45"}, {"puzzle": "8....3.7....6...9.......2...5.........7.451.....7...3...1..8.9....5......68.1.4..", "id": 381, "best": "00:10:23 ", "time": "00:40:45"}, {"puzzle": "8....3.7....6...9.......2...5.........7.451.....7...3...1..8.9....5......68.1.4..", "id": 382, "best": "00:10:23 ", "time": "00:40:45"}, {"puzzle": "8....3.7....6...9.......2...5.........7.451.....7...3...1..8.9....5......68.1.4..", "id": 383, "best": "00:10:23 ", "time": "00:40:45"}, {"puzzle": "8....3.7....6...9.......2...5.........7.451.....7...3...1..8.9....5......68.1.4..", "id": 384, "best": "00:10:23 ", "time": "00:40:45"}, {"puzzle": "8....3.7....6...9.......2...5.........7.451.....7...3...1..8.9....5......68.1.4..", "id": 385, "best": "00:10:23 ", "time": "00:40:45"}, {"puzzle": "8....3.7....6...9.......2...5.........7.451.....7...3...1..8.9....5......68.1.4..", "id": 386, "best": "00:10:23 ", "time": "00:40:45"}, {"puzzle": "8....3.7....6...9.......2...5.........7.451.....7...3...1..8.9....5......68.1.4..", "id": 387, "best": "00:10:23 ", "time": "00:40:45"}, {"puzzle": "8....3.7....6...9.......2...5.........7.451.....7...3...1..8.9....5......68.1.4..", "id": 388, "best": "00:10:23 ", "time": "00:40:45"}, {"puzzle": "8....3.7....6...9.......2...5.........7.451.....7...3...1..8.9....5......68.1.4..", "id": 389, "best": "00:10:23 ", "time": "00:40:45"}, {"puzzle": "8....3.7....6...9.......2...5.........7.451.....7...3...1..8.9....5......68.1.4..", "id": 390, "best": "00:10:23 ", "time": "00:40:45"}, {"puzzle": "8....3.7....6...9.......2...5.........7.451.....7...3...1..8.9....5......68.1.4..", "id": 391, "best": "00:10:23 ", "time": "00:40:45"}, {"puzzle": "8....3.7....6...9.......2...5.........7.451.....7...3...1..8.9....5......68.1.4..", "id": 392, "best": "00:10:23 ", "time": "00:40:45"}, {"puzzle": "8....3.7....6...9.......2...5.........7.451.....7...3...1..8.9....5......68.1.4..", "id": 393, "best": "00:10:23 ", "time": "00:40:45"}, {"puzzle": "8....3.7....6...9.......2...5.........7.451.....7...3...1..8.9....5......68.1.4..", "id": 394, "best": "00:10:23 ", "time": "00:40:45"}, {"puzzle": "8....3.7....6...9.......2...5.........7.451.....7...3...1..8.9....5......68.1.4..", "id": 395, "best": "00:10:23 ", "time": "00:40:45"}, {"puzzle": "8....3.7....6...9.......2...5.........7.451.....7...3...1..8.9....5......68.1.4..", "id": 396, "best": "00:10:23 ", "time": "00:40:45"}, {"puzzle": "8....3.7....6...9.......2...5.........7.451.....7...3...1..8.9....5......68.1.4..", "id": 397, "best": "00:10:23 ", "time": "00:40:45"}, {"puzzle": "8....3.7....6...9.......2...5.........7.451.....7...3...1..8.9....5......68.1.4..", "id": 398, "best": "00:10:23 ", "time": "00:40:45"}, {"puzzle": "8....3.7....6...9.......2...5.........7.451.....7...3...1..8.9....5......68.1.4..", "id": 399, "best": "00:10:23 ", "time": "00:40:45"}, {"puzzle": "8....3.7....6...9.......2...5.........7.451.....7...3...1..8.9....5......68.1.4..", "id": 400, "best": "00:10:23 ", "time": "00:40:45"}, {"puzzle": "8....3.7....6...9.......2...5.........7.451.....7...3...1..8.9....5......68.1.4..", "id": 401, "best": "00:10:23 ", "time": "00:40:45"}, {"puzzle": "8....3.7....6...9.......2...5.........7.451.....7...3...1..8.9....5......68.1.4..", "id": 402, "best": "00:10:23 ", "time": "00:40:45"}, {"puzzle": "8....3.7....6...9.......2...5.........7.451.....7...3...1..8.9....5......68.1.4..", "id": 403, "best": "00:10:23 ", "time": "00:40:45"}, {"puzzle": "8....3.7....6...9.......2...5.........7.451.....7...3...1..8.9....5......68.1.4..", "id": 404, "best": "00:10:23 ", "time": "00:40:45"}, {"puzzle": "8....3.7....6...9.......2...5.........7.451.....7...3...1..8.9....5......68.1.4..", "id": 405, "best": "00:10:23 ", "time": "00:40:45"}, {"puzzle": "8....3.7....6...9.......2...5.........7.451.....7...3...1..8.9....5......68.1.4..", "id": 406, "best": "00:10:23 ", "time": "00:40:45"}, {"puzzle": "8....3.7....6...9.......2...5.........7.451.....7...3...1..8.9....5......68.1.4..", "id": 407, "best": "00:10:23 ", "time": "00:40:45"}, {"puzzle": "8....3.7....6...9.......2...5.........7.451.....7...3...1..8.9....5......68.1.4..", "id": 408, "best": "00:10:23 ", "time": "00:40:45"}, {"puzzle": "8....3.7....6...9.......2...5.........7.451.....7...3...1..8.9....5......68.1.4..", "id": 409, "best": "00:10:23 ", "time": "00:40:45"}, {"puzzle": "8....3.7....6...9.......2...5.........7.451.....7...3...1..8.9....5......68.1.4..", "id": 410, "best": "00:10:23 ", "time": "00:40:45"}, {"puzzle": "8....3.7....6...9.......2...5.........7.451.....7...3...1..8.9....5......68.1.4..", "id": 411, "best": "00:10:23 ", "time": "00:40:45"}, {"puzzle": "8....3.7....6...9.......2...5.........7.451.....7...3...1..8.9....5......68.1.4..", "id": 412, "best": "00:10:23 ", "time": "00:40:45"}, {"puzzle": "8....3.7....6...9.......2...5.........7.451.....7...3...1..8.9....5......68.1.4..", "id": 413, "best": "00:10:23 ", "time": "00:40:45"}, {"puzzle": "8....3.7....6...9.......2...5.........7.451.....7...3...1..8.9....5......68.1.4..", "id": 414, "best": "00:10:23 ", "time": "00:40:45"}, {"puzzle": "8....3.7....6...9.......2...5.........7.451.....7...3...1..8.9....5......68.1.4..", "id": 415, "best": "00:10:23 ", "time": "00:40:45"}, {"puzzle": "8....3.7....6...9.......2...5.........7.451.....7...3...1..8.9....5......68.1.4..", "id": 416, "best": "00:10:23 ", "time": "00:40:45"}, {"puzzle": "8....3.7....6...9.......2...5.........7.451.....7...3...1..8.9....5......68.1.4..", "id": 417, "best": "00:10:23 ", "time": "00:40:45"}, {"puzzle": "8....3.7....6...9.......2...5.........7.451.....7...3...1..8.9....5......68.1.4..", "id": 418, "best": "00:10:23 ", "time": "00:40:45"}, {"puzzle": "8....3.7....6...9.......2...5.........7.451.....7...3...1..8.9....5......68.1.4..", "id": 419, "best": "00:10:23 ", "time": "00:40:45"}, {"puzzle": "8....3.7....6...9.......2...5.........7.451.....7...3...1..8.9....5......68.1.4..", "id": 420, "best": "00:10:23 ", "time": "00:40:45"}, {"puzzle": "8....3.7....6...9.......2...5.........7.451.....7...3...1..8.9....5......68.1.4..", "id": 421, "best": "00:10:23 ", "time": "00:40:45"}, {"puzzle": "8....3.7....6...9.......2...5.........7.451.....7...3...1..8.9....5......68.1.4..", "id": 422, "best": "00:10:23 ", "time": "00:40:45"}, {"puzzle": "8....3.7....6...9.......2...5.........7.451.....7...3...1..8.9....5......68.1.4..", "id": 423, "best": "00:10:23 ", "time": "00:40:45"}, {"puzzle": "8....3.7....6...9.......2...5.........7.451.....7...3...1..8.9....5......68.1.4..", "id": 424, "best": "00:10:23 ", "time": "00:40:45"}, {"puzzle": "8....3.7....6...9.......2...5.........7.451.....7...3...1..8.9....5......68.1.4..", "id": 425, "best": "00:10:23 ", "time": "00:40:45"}, {"puzzle": "8....3.7....6...9.......2...5.........7.451.....7...3...1..8.9....5......68.1.4..", "id": 426, "best": "00:10:23 ", "time": "00:40:45"}, {"puzzle": "8....3.7....6...9.......2...5.........7.451.....7...3...1..8.9....5......68.1.4..", "id": 427, "best": "00:10:23 ", "time": "00:40:45"}, {"puzzle": "8....3.7....6...9.......2...5.........7.451.....7...3...1..8.9....5......68.1.4..", "id": 428, "best": "00:10:23 ", "time": "00:40:45"}, {"puzzle": "8....3.7....6...9.......2...5.........7.451.....7...3...1..8.9....5......68.1.4..", "id": 429, "best": "00:10:23 ", "time": "00:40:45"}, {"puzzle": "8....3.7....6...9.......2...5.........7.451.....7...3...1..8.9....5......68.1.4..", "id": 430, "best": "00:10:23 ", "time": "00:40:45"}, {"puzzle": "8....3.7....6...9.......2...5.........7.451.....7...3...1..8.9....5......68.1.4..", "id": 431, "best": "00:10:23 ", "time": "00:40:45"}, {"puzzle": "8....3.7....6...9.......2...5.........7.451.....7...3...1..8.9....5......68.1.4..", "id": 432, "best": "00:10:23 ", "time": "00:40:45"}, {"puzzle": "8....3.7....6...9.......2...5.........7.451.....7...3...1..8.9....5......68.1.4..", "id": 433, "best": "00:10:23 ", "time": "00:40:45"}, {"puzzle": "8....3.7....6...9.......2...5.........7.451.....7...3...1..8.9....5......68.1.4..", "id": 434, "best": "00:10:23 ", "time": "00:40:45"}, {"puzzle": "8....3.7....6...9.......2...5.........7.451.....7...3...1..8.9....5......68.1.4..", "id": 435, "best": "00:10:23 ", "time": "00:40:45"}, {"puzzle": "8....3.7....6...9.......2...5.........7.451.....7...3...1..8.9....5......68.1.4..", "id": 436, "best": "00:10:23 ", "time": "00:40:45"}, {"puzzle": "8....3.7....6...9.......2...5.........7.451.....7...3...1..8.9....5......68.1.4..", "id": 437, "best": "00:10:23 ", "time": "00:40:45"}, {"puzzle": "8....3.7....6...9.......2...5.........7.451.....7...3...1..8.9....5......68.1.4..", "id": 438, "best": "00:10:23 ", "time": "00:40:45"}, {"puzzle": "8....3.7....6...9.......2...5.........7.451.....7...3...1..8.9....5......68.1.4..", "id": 439, "best": "00:10:23 ", "time": "00:40:45"}, {"puzzle": "8....3.7....6...9.......2...5.........7.451.....7...3...1..8.9....5......68.1.4..", "id": 440, "best": "00:10:23 ", "time": "00:40:45"}, {"puzzle": "8....3.7....6...9.......2...5.........7.451.....7...3...1..8.9....5......68.1.4..", "id": 441, "best": "00:10:23 ", "time": "00:40:45"}, {"puzzle": "8....3.7....6...9.......2...5.........7.451.....7...3...1..8.9....5......68.1.4..", "id": 442, "best": "00:10:23 ", "time": "00:40:45"}, {"puzzle": "8....3.7....6...9.......2...5.........7.451.....7...3...1..8.9....5......68.1.4..", "id": 443, "best": "00:10:23 ", "time": "00:40:45"}, {"puzzle": "8....3.7....6...9.......2...5.........7.451.....7...3...1..8.9....5......68.1.4..", "id": 444, "best": "00:10:23 ", "time": "00:40:45"}, {"puzzle": "8....3.7....6...9.......2...5.........7.451.....7...3...1..8.9....5......68.1.4..", "id": 445, "best": "00:10:23 ", "time": "00:40:45"}, {"puzzle": "8....3.7....6...9.......2...5.........7.451.....7...3...1..8.9....5......68.1.4..", "id": 446, "best": "00:10:23 ", "time": "00:40:45"}, {"puzzle": "8....3.7....6...9.......2...5.........7.451.....7...3...1..8.9....5......68.1.4..", "id": 447, "best": "00:10:23 ", "time": "00:40:45"}, {"puzzle": "8....3.7....6...9.......2...5.........7.451.....7...3...1..8.9....5......68.1.4..", "id": 448, "best": "00:10:23 ", "time": "00:40:45"}, {"puzzle": "8....3.7....6...9.......2...5.........7.451.....7...3...1..8.9....5......68.1.4..", "id": 449, "best": "00:10:23 ", "time": "00:40:45"}, {"puzzle": "8....3.7....6...9.......2...5.........7.451.....7...3...1..8.9....5......68.1.4..", "id": 450, "best": "00:10:23 ", "time": "00:40:45"}, {"puzzle": "8....3.7....6...9.......2...5.........7.451.....7...3...1..8.9....5......68.1.4..", "id": 451, "best": "00:10:23 ", "time": "00:40:45"}, {"puzzle": "8....3.7....6...9.......2...5.........7.451.....7...3...1..8.9....5......68.1.4..", "id": 452, "best": "00:10:23 ", "time": "00:40:45"}, {"puzzle": "8....3.7....6...9.......2...5.........7.451.....7...3...1..8.9....5......68.1.4..", "id": 453, "best": "00:10:23 ", "time": "00:40:45"}, {"puzzle": "8....3.7....6...9.......2...5.........7.451.....7...3...1..8.9....5......68.1.4..", "id": 454, "best": "00:10:23 ", "time": "00:40:45"}, {"puzzle": "8....3.7....6...9.......2...5.........7.451.....7...3...1..8.9....5......68.1.4..", "id": 455, "best": "00:10:23 ", "time": "00:40:45"}, {"puzzle": "8....3.7....6...9.......2...5.........7.451.....7...3...1..8.9....5......68.1.4..", "id": 456, "best": "00:10:23 ", "time": "00:40:45"}, {"puzzle": "8....3.7....6...9.......2...5.........7.451.....7...3...1..8.9....5......68.1.4..", "id": 457, "best": "00:10:23 ", "time": "00:40:45"}, {"puzzle": "8....3.7....6...9.......2...5.........7.451.....7...3...1..8.9....5......68.1.4..", "id": 458, "best": "00:10:23 ", "time": "00:40:45"}, {"puzzle": "8....3.7....6...9.......2...5.........7.451.....7...3...1..8.9....5......68.1.4..", "id": 459, "best": "00:10:23 ", "time": "00:40:45"}, {"puzzle": "8....3.7....6...9.......2...5.........7.451.....7...3...1..8.9....5......68.1.4..", "id": 460, "best": "00:10:23 ", "time": "00:40:45"}, {"puzzle": "8....3.7....6...9.......2...5.........7.451.....7...3...1..8.9....5......68.1.4..", "id": 461, "best": "00:10:23 ", "time": "00:40:45"}, {"puzzle": "8....3.7....6...9.......2...5.........7.451.....7...3...1..8.9....5......68.1.4..", "id": 462, "best": "00:10:23 ", "time": "00:40:45"}, {"puzzle": "8....3.7....6...9.......2...5.........7.451.....7...3...1..8.9....5......68.1.4..", "id": 463, "best": "00:10:23 ", "time": "00:40:45"}, {"puzzle": "8....3.7....6...9.......2...5.........7.451.....7...3...1..8.9....5......68.1.4..", "id": 464, "best": "00:10:23 ", "time": "00:40:45"}, {"puzzle": "8....3.7....6...9.......2...5.........7.451.....7...3...1..8.9....5......68.1.4..", "id": 465, "best": "00:10:23 ", "time": "00:40:45"}, {"puzzle": "8....3.7....6...9.......2...5.........7.451.....7...3...1..8.9....5......68.1.4..", "id": 466, "best": "00:10:23 ", "time": "00:40:45"}, {"puzzle": "8....3.7....6...9.......2...5.........7.451.....7...3...1..8.9....5......68.1.4..", "id": 467, "best": "00:10:23 ", "time": "00:40:45"}, {"puzzle": "8....3.7....6...9.......2...5.........7.451.....7...3...1..8.9....5......68.1.4..", "id": 468, "best": "00:10:23 ", "time": "00:40:45"}, {"puzzle": "8....3.7....6...9.......2...5.........7.451.....7...3...1..8.9....5......68.1.4..", "id": 469, "best": "00:10:23 ", "time": "00:40:45"}, {"puzzle": "8....3.7....6...9.......2...5.........7.451.....7...3...1..8.9....5......68.1.4..", "id": 470, "best": "00:10:23 ", "time": "00:40:45"}, {"puzzle": "8....3.7....6...9.......2...5.........7.451.....7...3...1..8.9....5......68.1.4..", "id": 471, "best": "00:10:23 ", "time": "00:40:45"}, {"puzzle": "8....3.7....6...9.......2...5.........7.451.....7...3...1..8.9....5......68.1.4..", "id": 472, "best": "00:10:23 ", "time": "00:40:45"}, {"puzzle": "8....3.7....6...9.......2...5.........7.451.....7...3...1..8.9....5......68.1.4..", "id": 473, "best": "00:10:23 ", "time": "00:40:45"}, {"puzzle": "8....3.7....6...9.......2...5.........7.451.....7...3...1..8.9....5......68.1.4..", "id": 474, "best": "00:10:23 ", "time": "00:40:45"}, {"puzzle": "8....3.7....6...9.......2...5.........7.451.....7...3...1..8.9....5......68.1.4..", "id": 475, "best": "00:10:23 ", "time": "00:40:45"}, {"puzzle": "8....3.7....6...9.......2...5.........7.451.....7...3...1..8.9....5......68.1.4..", "id": 476, "best": "00:10:23 ", "time": "00:40:45"}, {"puzzle": "8....3.7....6...9.......2...5.........7.451.....7...3...1..8.9....5......68.1.4..", "id": 477, "best": "00:10:23 ", "time": "00:40:45"}, {"puzzle": "8....3.7....6...9.......2...5.........7.451.....7...3...1..8.9....5......68.1.4..", "id": 478, "best": "00:10:23 ", "time": "00:40:45"}, {"puzzle": "8....3.7....6...9.......2...5.........7.451.....7...3...1..8.9....5......68.1.4..", "id": 479, "best": "00:10:23 ", "time": "00:40:45"}, {"puzzle": "8....3.7....6...9.......2...5.........7.451.....7...3...1..8.9....5......68.1.4..", "id": 480, "best": "00:10:23 ", "time": "00:40:45"}, {"puzzle": "8....3.7....6...9.......2...5.........7.451.....7...3...1..8.9....5......68.1.4..", "id": 481, "best": "00:10:23 ", "time": "00:40:45"}, {"puzzle": "8....3.7....6...9.......2...5.........7.451.....7...3...1..8.9....5......68.1.4..", "id": 482, "best": "00:10:23 ", "time": "00:40:45"}, {"puzzle": "8....3.7....6...9.......2...5.........7.451.....7...3...1..8.9....5......68.1.4..", "id": 483, "best": "00:10:23 ", "time": "00:40:45"}, {"puzzle": "8....3.7....6...9.......2...5.........7.451.....7...3...1..8.9....5......68.1.4..", "id": 484, "best": "00:10:23 ", "time": "00:40:45"}, {"puzzle": "8....3.7....6...9.......2...5.........7.451.....7...3...1..8.9....5......68.1.4..", "id": 485, "best": "00:10:23 ", "time": "00:40:45"}, {"puzzle": "8....3.7....6...9.......2...5.........7.451.....7...3...1..8.9....5......68.1.4..", "id": 486, "best": "00:10:23 ", "time": "00:40:45"}, {"puzzle": "8....3.7....6...9.......2...5.........7.451.....7...3...1..8.9....5......68.1.4..", "id": 487, "best": "00:10:23 ", "time": "00:40:45"}, {"puzzle": "8....3.7....6...9.......2...5.........7.451.....7...3...1..8.9....5......68.1.4..", "id": 488, "best": "00:10:23 ", "time": "00:40:45"}, {"puzzle": "8....3.7....6...9.......2...5.........7.451.....7...3...1..8.9....5......68.1.4..", "id": 489, "best": "00:10:23 ", "time": "00:40:45"}, {"puzzle": "8....3.7....6...9.......2...5.........7.451.....7...3...1..8.9....5......68.1.4..", "id": 490, "best": "00:10:23 ", "time": "00:40:45"}, {"puzzle": "8....3.7....6...9.......2...5.........7.451.....7...3...1..8.9....5......68.1.4..", "id": 491, "best": "00:10:23 ", "time": "00:40:45"}, {"puzzle": "8....3.7....6...9.......2...5.........7.451.....7...3...1..8.9....5......68.1.4..", "id": 492, "best": "00:10:23 ", "time": "00:40:45"}, {"puzzle": "8....3.7....6...9.......2...5.........7.451.....7...3...1..8.9....5......68.1.4..", "id": 493, "best": "00:10:23 ", "time": "00:40:45"}, {"puzzle": "8....3.7....6...9.......2...5.........7.451.....7...3...1..8.9....5......68.1.4..", "id": 494, "best": "00:10:23 ", "time": "00:40:45"}, {"puzzle": "8....3.7....6...9.......2...5.........7.451.....7...3...1..8.9....5......68.1.4..", "id": 495, "best": "00:10:23 ", "time": "00:40:45"}, {"puzzle": "8....3.7....6...9.......2...5.........7.451.....7...3...1..8.9....5......68.1.4..", "id": 496, "best": "00:10:23 ", "time": "00:40:45"}, {"puzzle": "8....3.7....6...9.......2...5.........7.451.....7...3...1..8.9....5......68.1.4..", "id": 497, "best": "00:10:23 ", "time": "00:40:45"}, {"puzzle": "8....3.7....6...9.......2...5.........7.451.....7...3...1..8.9....5......68.1.4..", "id": 498, "best": "00:10:23 ", "time": "00:40:45"}, {"puzzle": "8....3.7....6...9.......2...5.........7.451.....7...3...1..8.9....5......68.1.4..", "id": 499, "best": "00:10:23 ", "time": "00:40:45"}]